Metadata-Version: 2.1
Name: datasette-sqlite-path
Version: 0.2.1
Home-page: https://github.com/asg017/sqlite-path
Author: Alex Garcia
License: MIT License, Apache License, Version 2.0
Project-URL: Issues, https://github.com/asg017/sqlite-path/issues
Project-URL: CI, https://github.com/asg017/sqlite-path/actions
Project-URL: Changelog, https://github.com/asg017/sqlite-path/releases
Requires-Python: >=3.7
Requires-Dist: datasette
Requires-Dist: sqlite-path
Provides-Extra: test
Requires-Dist: pytest ; extra == 'test'
